{
  "hash": "424a3de26357bf243c421b2f69bc7c4a",
  "result": {
    "engine": "knitr",
    "markdown": "---\ntitle: \"Drug-related Arrests and Possible Overdoses\"\nformat:\n  html:\n    embed-resources: true\nproject:\n  output-dir: \"E:/EMS_calls/News_searches/GitHub/CHQ_Report_GitHub_Actions/twentyandchange.github.io/CHQ_Report_W-Tba4YQG\"\neditor: visual\nwarning: false\nexecute:\n  warning: false\n  message: false\ninclude-in-header:\n  - text: |\n      <link rel = \"shortcut icon\" href = \"favicon_1.svg\" />\n---\n\n\n\n::: callout-note\n### NOT FOR CIRCULATION\n:::\n\n------------------------------------------------------------------------\n\n### A summary compilation for the 7 days ending April 18, 2025\n\n------------------------------------------------------------------------\n\n## Published news articles: {#news}\n\n\n\n::: {.cell}\n\n:::\n\n\n<ul>\n  <li><a href=\"https://mediaonegroupradio.com/news-and-closings/local-news-headlines/789119/wjtn-news-headlines-for-thurs-apr-17-2025\" target=\"_blank\">3 keyword references (WJTN)</a></li>\n  <li><a href=\"https://wnynewsnow.com/2025/04/18/three-arrested-in-salamanca-drug-investigation-following-early-morning-traffic-stop/\" target=\"_blank\">Three Arrested in Salamanca Drug Investigation Following Early Morning Traffic Stop</a></li>\n  <li><a href=\"https://mediaonegroupradio.com/news-and-closings/local-news-headlines/788937/wjtn-news-headlines-for-wed-apr-16-2025\" target=\"_blank\">1 keyword references (WJTN)</a></li>\n  <li><a href=\"https://wnynewsnow.com/2025/04/17/attorney-general-james-secures-convictions-in-major-upstate-ny-drug-trafficking-case/\" target=\"_blank\">Attorney General James Secures Convictions in Major Upstate NY Drug Trafficking Case</a></li>\n  <li><a href=\"https://tinyurl.com/227jtg3j\" target=\"_blank\">Olean Man Indicted For Role In Jamestown Drug Conspiracy - WRFA-LP 107.9 FM</a></li>\n  <li><a href=\"https://mediaonegroupradio.com/news-and-closings/local-news-headlines/788471/wjtn-news-headlines-for-mon-apr-14-2025\" target=\"_blank\">0 keyword references (WJTN)</a></li>\n  <li><a href=\"https://chautauquatoday.com/blotter/details.cfm?clientid=25&id=363603\" target=\"_blank\">NA</a></li>\n  <li><a href=\"https://mediaonegroupradio.com/news-and-closings/local-news-headlines/788300/wjtn-news-headlines-for-fri-apr-11-2025\" target=\"_blank\">4 keyword references (WJTN)</a></li>\n</ul>\n\n\n\n######## *(Note: \"\\_\\_ keyword references (WJTN)\" refers to the number of drug-related terms present in that news posting.)*\n\n------------------------------------------------------------------------\n\n## EMS dispatches - possible overdoses: {#ods}\n\n\n\n::: {.cell}\n::: {.cell-output-display}\n\n```{=html}\n<div class=\"leaflet html-widget html-fill-item\" id=\"htmlwidget-3b8e4ae642905c76ee45\" style=\"width:100%;height:464px;\"></div>\n<script type=\"application/json\" data-for=\"htmlwidget-3b8e4ae642905c76ee45\">{\"x\":{\"options\":{\"crs\":{\"crsClass\":\"L.CRS.EPSG3857\",\"code\":null,\"proj4def\":null,\"projectedBounds\":null,\"options\":{}}},\"calls\":[{\"method\":\"addTiles\",\"args\":[\"https://{s}.tile.openstreetmap.org/{z}/{x}/{y}.png\",null,null,{\"minZoom\":0,\"maxZoom\":18,\"tileSize\":256,\"subdomains\":\"abc\",\"errorTileUrl\":\"\",\"tms\":false,\"noWrap\":false,\"zoomOffset\":0,\"zoomReverse\":false,\"opacity\":1,\"zIndex\":1,\"detectRetina\":false,\"attribution\":\"&copy; <a href=\\\"https://openstreetmap.org/copyright/\\\">OpenStreetMap<\\/a>,  <a href=\\\"https://opendatacommons.org/licenses/odbl/\\\">ODbL<\\/a>\"}]},{\"method\":\"addMarkers\",\"args\":[[42.1189591132123,42.0969651240577,42.1017042948587,42.4536389072978,42.1003089308658,42.0865709897267],[-79.19726547356851,-79.23921928243411,-79.2378686817985,-79.33476175595131,-79.2327341166541,-79.715192292701],null,null,null,{\"interactive\":true,\"draggable\":false,\"keyboard\":true,\"title\":\"\",\"alt\":\"\",\"zIndexOffset\":0,\"opacity\":1,\"riseOnHover\":false,\"riseOffset\":250},[\" 2 E MAIN <br> <br>  Falconer: *EMS ALS FEMALE ATTEMPTED TO OVERDOSE, EPD ON SCENE <br> <br>  2025-04-17 11:23:49\",\" 311  SPRING <br> <br>  Jamestown: Assist Fire/Rescue 2 UNRESPONSIVE SUBJECTS IN THE STAIRWELL SPRING ST SIDE <br> <br>  2025-04-15 13:43:12\",\" 221 E 8TH <br> <br>  Jamestown: Assist Fire/Rescue APT 3 ; 44/F - POSSIBLE OVERDOSE, SEMI RESPONSIVE <br> <br>  2025-04-15 03:50:15\",\" 280  CENTRAL <br> <br>  Fredonia: *EMS ALS CHAUTAUQUA HALL . POSS OVERDOSE <br> <br>  2025-04-14 20:35:30\",\" 628 E 6TH <br> <br>  Jamestown: *EMS ALS JPD ON SCENE, MALE POSSIBLE OD ON TYLENOL <br> <br>  2025-04-14 10:23:25\",\" 2001  RT426 <br> <br>  Findley Lake: *EMS ALS 24YO MALE OVERDOSE ON SEVERAL BOTTLES OF PILLS, SEMI RESPONSIVE <br> <br>  2025-04-13 14:13:10\"],null,null,null,null,{\"interactive\":false,\"permanent\":false,\"direction\":\"auto\",\"opacity\":1,\"offset\":[0,0],\"textsize\":\"10px\",\"textOnly\":false,\"className\":\"\",\"sticky\":true},null]}],\"limits\":{\"lat\":[42.0865709897267,42.4536389072978],\"lng\":[-79.715192292701,-79.19726547356851]}},\"evals\":[],\"jsHooks\":[]}</script>\n```\n\n:::\n:::\n",
    "supporting": [],
    "filters": [
      "rmarkdown/pagebreak.lua"
    ],
    "includes": {
      "include-in-header": [
        "<link href=\"site_libs/htmltools-fill-0.5.8.1/fill.css\" rel=\"stylesheet\" />\n<script src=\"site_libs/htmlwidgets-1.6.4/htmlwidgets.js\"></script>\n<script src=\"site_libs/jquery-3.6.0/jquery-3.6.0.min.js\"></script>\n<link href=\"site_libs/leaflet-1.3.1/leaflet.css\" rel=\"stylesheet\" />\n<script src=\"site_libs/leaflet-1.3.1/leaflet.js\"></script>\n<link href=\"site_libs/leafletfix-1.0.0/leafletfix.css\" rel=\"stylesheet\" />\n<script src=\"site_libs/proj4-2.6.2/proj4.min.js\"></script>\n<script src=\"site_libs/Proj4Leaflet-1.0.1/proj4leaflet.js\"></script>\n<link href=\"site_libs/rstudio_leaflet-1.3.1/rstudio_leaflet.css\" rel=\"stylesheet\" />\n<script src=\"site_libs/leaflet-binding-2.2.2/leaflet.js\"></script>\n"
      ]
    },
    "engineDependencies": {},
    "preserve": {},
    "postProcess": true
  }
}